odoo/addons/hr_leave_type_code/README.rst
odoo/addons/hr_leave_type_code/__init__.py
odoo/addons/hr_leave_type_code/__manifest__.py
odoo/addons/hr_leave_type_code/i18n/es.po
odoo/addons/hr_leave_type_code/i18n/hr_leave_type_code.pot
odoo/addons/hr_leave_type_code/i18n/it.po
odoo/addons/hr_leave_type_code/models/__init__.py
odoo/addons/hr_leave_type_code/models/hr_leave_type.py
odoo/addons/hr_leave_type_code/readme/CONTRIBUTORS.rst
odoo/addons/hr_leave_type_code/readme/DESCRIPTION.rst
odoo/addons/hr_leave_type_code/readme/USAGE.rst
odoo/addons/hr_leave_type_code/static/description/icon.png
odoo/addons/hr_leave_type_code/static/description/index.html
odoo/addons/hr_leave_type_code/tests/__init__.py
odoo/addons/hr_leave_type_code/tests/test_hr_leave_type_code.py
odoo/addons/hr_leave_type_code/views/hr_leave_type.xml
odoo_addon_hr_leave_type_code-16.0.1.0.0.6.dist-info/METADATA
odoo_addon_hr_leave_type_code-16.0.1.0.0.6.dist-info/WHEEL
odoo_addon_hr_leave_type_code-16.0.1.0.0.6.dist-info/top_level.txt
odoo_addon_hr_leave_type_code-16.0.1.0.0.6.dist-info/RECORD
